{
"type": "FeatureCollection",
"crs": { "type": "name", "properties": { "name": "urn:ogc:def:crs:OGC:1.3:CRS84" } },
                                                                                                                                  
"features": [
{ "type": "Feature", "properties": { "Plaats": "Budel", "Lat": 51.289678, "Lon": 5.631302, "Naam": "Budel-Cranendonck", "Type": "Azc", "Opvangplaatsen": 1500, "Straat": "Randweg-Oost", "Huisnummer": 32, "Postcode": "6021PB", "Telefoon": "088-7155800", "Email": null, "Noodopvang": "Nee", "Beschrijving": "De opvanglocatie in Budel-Cranendonck is gevestigd in de voormalige De Nassau-Dietzkazerne. Een kazerne in het dorp Budel, een van de kernen van de gemeente Cranendonck.  Het COA vangt hier sinds mei 2014 asielzoekers op. Er is plek voor maximaal 1500 bewoners. Het is gedeelde locatie in de zin dat een deel van het complex wordt ingezet als regulier azc en een deel als een POL-locatie.  In de POL staan de bewoners  aan het begin staan van hun asielprocedure. Een POL bevindt zich altijd in de buurt van het kantoor van de IND waar de asielaanvraag in behandeling is. In de POL is met name aandacht voor gesprekken tussen asielzoekers en advocaten, Voorlichting door Vluchtelingenwerk Nederland voorlichting over de opvang en de medische dienst.  Op de locatie zijn een basisschool en een school voor voortgezetonderwijs aanwezig. Daarnaast is er ook veel ruimte voor sport en spel.", "Huisletter": null, "Beschikbaar tot": null }, "geometry": { "type": "Point", "coordinates": [ 5.63130169558886, 51.289677525725999 ] } },
{ "type": "Feature", "properties": { "Plaats": "Budel-Dorplein", "Lat": 51.236395, "Lon": 5.591400, "Naam": "Budel-Dorplein", "Type": "Azc", "Opvangplaatsen": 239, "Straat": "Hoofdstraat ", "Huisnummer": 80, "Postcode": "6024AA", "Telefoon": "088-7152400", "Email": null, "Noodopvang": "Nee", "Beschrijving": "Het azc in Budel-Dorplein is gevestigd in het gebouw De Cantine in Budel-Dorplein. De eerste asielzoekers zijn 28 april 2014 ingestroomd.  Het gebouw De Cantine werd eerder gebruikt voor de opvang van asielzoekers, maar werd in 2011 gesloten vanwege overcapaciteit. Gezien de verhoogde instroom van asielzoekers wordt het weer in gebruik genomen. Het gebouw is gerenoveerd om het gereed te maken voor bewoners.  Het COA heeft met de gemeente een overeenkomst voor onbepaalde tijd gesloten. Het asielzoekers-centrum biedt plaats aan 239 asielzoekers.", "Huisletter": null, "Beschikbaar tot": null }, "geometry": { "type": "Point", "coordinates": [ 5.59140033968709, 51.236394606344398 ] } },
{ "type": "Feature", "properties": { "Plaats": "Eindhoven", "Lat": 51.492372, "Lon": 5.456358, "Naam": "Eindhoven", "Type": "Azc", "Opvangplaatsen": 700, "Straat": "Castilielaan", "Huisnummer": 15, "Postcode": "5629CH", "Telefoon": "088 71 56 100", "Email": "eindhoven@coa.nl", "Noodopvang": "Nee", "Beschrijving": "azc Eindhoven is gelegen in de tijdelijke wooneenheid 'De Orangerie' aan de Castiliëlaan in Eindhoven en biedt onderdak aan maximaal 700 asielzoekers. De locatie zal naar verwachting 2 jaar in gebruik zijn als opvang voor asielzoekers. Ondertussen gaat het COA samen met de gemeente op zoek naar een vervangende locatie.", "Huisletter": null, "Beschikbaar tot": null }, "geometry": { "type": "Point", "coordinates": [ 5.45635815542878, 51.4923722941571 ] } }
]
}
