{
"type": "FeatureCollection",
"crs": { "type": "name", "properties": { "name": "urn:ogc:def:crs:OGC:1.3:CRS84" } },
                                                                                                                                  
"features": [
{ "type": "Feature", "properties": { "Plaats": "Almere", "Lat": 52.391100, "Lon": 5.250605, "Naam": "Almere", "Type": "Azc", "Opvangplaatsen": 800, "Straat": "Engelse mijl", "Huisnummer": 6, "Postcode": "1318EN", "Telefoon": "088-7153900", "Email": "almere@coa.nl", "Noodopvang": "Nee", "Beschrijving": "Het azc Almere is sinds het jaar 2000 in gebruik. In de periode 2006-2010 heeft het COA, dat eigenaar is van het terrein, tussentijds de gebouwen verhuurd aan verschillende maatschappelijke organisaties, met de afspraak dat de organisaties tijdelijk gebruik konden maken van de ruimtes. Zo ontstond het Biathlon Woonpark, waar diverse groepen mensen woonden of alleen overdag verbleven. De locatiemanager van het azc is Amanda Steeneveld. Voor mogelijk vrijwilligerswerk kan contact opgenomen worden met het team Wonen van het azc. Zowel de gebouwen voor het personeel en externen als de bewonersgebouwen zijn opgebouwd uit prefab. De semipermanente bewonersgebouwen bestaan uit een onder en bovenverdieping met woonunits. Per unit wonen 6-8 mensen.", "Huisletter": null, "Beschikbaar tot": null }, "geometry": { "type": "Point", "coordinates": [ 5.25060481400218, 52.391100021790599 ] } },
{ "type": "Feature", "properties": { "Plaats": "Dronten", "Lat": 52.545310, "Lon": 5.845657, "Naam": "Dronten", "Type": "Acz", "Opvangplaatsen": 1300, "Straat": "Vossemeerdijk", "Huisnummer": 40, "Postcode": "8251PN", "Telefoon": "088-7156500", "Email": "dronten@coa.nl", "Noodopvang": "Nee", "Beschrijving": "Azc Dronten is sinds 1994 in gebruik als opvanglocatie voor vluchtelingen. Het azc ligt aan de Roggebotsluis, halverwege Kampen en Dronten, op de plek waar de polder begint. Het azc werd in 2012 duurzaam herontwikkeld. De oude Finse bungalows zijn vervangen  door 134 duurzame huisjes die elk plaats bieden aan maximaal acht asielzoekers. In 2014 zijn er tijdelijk woonunits bijgeplaatst voor nog eens 300 mensen. De totale capaciteit van azc Dronten is 1.300.", "Huisletter": null, "Beschikbaar tot": null }, "geometry": { "type": "Point", "coordinates": [ 5.84565749294046, 52.5453100162025 ] } },
{ "type": "Feature", "properties": { "Plaats": "Luttelgeest", "Lat": 52.763816, "Lon": 5.820845, "Naam": "Luttelgeest", "Type": "Acz", "Opvangplaatsen": 1400, "Straat": "Oosterringweg", "Huisnummer": 41, "Postcode": "8315PS", "Telefoon": "088-7159100", "Email": "luttelgeest@coa.nl", "Noodopvang": "Nee", "Beschrijving": "Azc Luttelgeest is sinds 1987 in gebruik als asielzoekerscentrum en was voorheen een recreatiepark. Het azc is één van de eerst geopende  asielzoekerscentra in Nederland. In 2011 is gestart met een gefaseerde  duurzame herontwikkeling van het azc. De bewoners worden gehuisvest in 139 nieuwe huisjes. Het gebouw uit de tijd dat de Noordoostpolder werd drooggelegd is behouden en de nieuwe huisjes worden opgetrokken in de sfeer van de oude pionierswoningen. Er kunnen 1.000 mensen in worden opgevangen. In 2015 zijn er tijdelijke woonunits bijgeplaatst, waar 400 mensen in kunnen worden opgevangen. De totale opvangcapaciteit van deze locatie is 1.400. ", "Huisletter": null, "Beschikbaar tot": null }, "geometry": { "type": "Point", "coordinates": [ 5.82084450398217, 52.7638164570822 ] } }
]
}
