{
"type": "FeatureCollection",
"crs": { "type": "name", "properties": { "name": "urn:ogc:def:crs:OGC:1.3:CRS84" } },
                                                                                                                                  
"features": [
{ "type": "Feature", "properties": { "X": 191368, "Y": 314097, "X-nav": 191381, "Y-nav": 314135, "BAG Id": "1729010001049381", "Organisati": "RAV Zuid-Limburg", "LOC_TYPE": "Ambulancepost", "LOC_NAAM": "Gulpen", "LOC_STRAAT": "Oude Rijksweg", "Huisnr": "32", "Postcode": "6271 AA", "Plaats": "Gulpen", "GEM": "Gulpen-Wittem", "Regio": 24, "Website": "www.ggdzl.nl\/client\/1\/?websiteid=1&contentid=21&pagetitle=Ambulance", "Telefoon": "045-8506660", "CODE": null, "BIJZONDERH": "Imergis" }, "geometry": { "type": "Point", "coordinates": [ 5.9032142, 50.8155979 ] } },
{ "type": "Feature", "properties": { "X": 195976, "Y": 322159, "X-nav": 195993, "Y-nav": 322108, "BAG Id": "0917010000010762", "Organisati": "RAV Zuid-Limburg", "LOC_TYPE": "Ambulancepost", "LOC_NAAM": "Heerlen", "LOC_STRAAT": "Het Overloon", "Huisnr": "2", "Postcode": "6411 TE", "Plaats": "Heerlen", "GEM": "Heerlen", "Regio": 24, "Website": "www.ggdzl.nl\/client\/1\/?websiteid=1&contentid=21&pagetitle=Ambulance", "Telefoon": "045-8506660", "CODE": null, "BIJZONDERH": "Imergis" }, "geometry": { "type": "Point", "coordinates": [ 5.9695031, 50.8877519 ] } },
{ "type": "Feature", "properties": { "X": 177345, "Y": 316511, "X-nav": 177351, "Y-nav": 316450, "BAG Id": "0935010000071017", "Organisati": "RAV Zuid-Limburg", "LOC_TYPE": "Ambulancepost", "LOC_NAAM": "Maastricht", "LOC_STRAAT": "Gelissendomein", "Huisnr": "8", "Postcode": "6229 GJ", "Plaats": "Maastricht", "GEM": "Maastricht", "Regio": 24, "Website": "www.ggdzl.nl\/client\/1\/?websiteid=1&contentid=21&pagetitle=Ambulance", "Telefoon": "045-8506660", "CODE": null, "BIJZONDERH": "Imergis" }, "geometry": { "type": "Point", "coordinates": [ 5.704398, 50.8380139 ] } },
{ "type": "Feature", "properties": { "X": 186866, "Y": 332829, "X-nav": 186771, "Y-nav": 332935, "BAG Id": "1883010000009770", "Organisati": "RAV Zuid-Limburg", "LOC_TYPE": "Ambulancepost", "LOC_NAAM": "Geleen", "LOC_STRAAT": "Dr. H. van der Hoffplein", "Huisnr": "1", "Postcode": "6162 BG", "Plaats": "Geleen", "GEM": "Sittard-Geleen", "Regio": 24, "Website": "www.ggdzl.nl\/client\/1\/?websiteid=1&contentid=21&pagetitle=Ambulance", "Telefoon": "045-8506660", "CODE": null, "BIJZONDERH": "Imergis" }, "geometry": { "type": "Point", "coordinates": [ 5.8409874, 50.9842392 ] } }
]
}
