{
"type": "FeatureCollection",
"crs": { "type": "name", "properties": { "name": "urn:ogc:def:crs:OGC:1.3:CRS84" } },
                                                                                                                                  
"features": [
{ "type": "Feature", "properties": { "Naam": "C2000 mast", "Lat": 52.224240, "Lon": 5.178710 }, "geometry": { "type": "Point", "coordinates": [ 5.17871, 52.22424 ] } },
{ "type": "Feature", "properties": { "Naam": "C2000 mast", "Lat": 52.307370, "Lon": 5.237380 }, "geometry": { "type": "Point", "coordinates": [ 5.23738, 52.30737 ] } },
{ "type": "Feature", "properties": { "Naam": "C2000 mast", "Lat": 52.291480, "Lon": 5.169940 }, "geometry": { "type": "Point", "coordinates": [ 5.16994, 52.29148 ] } },
{ "type": "Feature", "properties": { "Naam": "C2000 mast", "Lat": 52.302050, "Lon": 5.022550 }, "geometry": { "type": "Point", "coordinates": [ 5.02255, 52.30205 ] } },
{ "type": "Feature", "properties": { "Naam": "C2000 mast", "Lat": 52.184810, "Lon": 5.179390 }, "geometry": { "type": "Point", "coordinates": [ 5.17939, 52.18481 ] } }
]
}
